{
    "$schema": "https://slimhuys.nl/schemas/dynamic-tariffs-nl/v2.json",
    "generated_at": "2026-07-17T04:00:09+02:00",
    "source_url": "https://slimhuys.nl/v1/suppliers",
    "license": "CC-BY-4.0",
    "maintainer": "SlimHuys (https://slimhuys.nl)",
    "supplier": {
        "slug": "zondergas",
        "name": "ZonderGas",
        "active": true,
        "official_api": false,
        "verified_at": "2026-07-13",
        "sources": [
            "https://eerlijkverbruik.nl/energie/zondergas"
        ],
        "params": {
            "billing_resolution_minutes": 15,
            "markup_eur_per_kwh": 0.034,
            "monthly_fee_eur": 6.49,
            "monthly_fee_electricity_only_eur": null
        },
        "default_gas_rate_eur_m3": null,
        "pricing_spec": {
            "version": 1,
            "consumed": {
                "epex": "quarter",
                "pipeline": [
                    {
                        "op": "add",
                        "ref": "tax.energy_tax_electricity",
                        "label": "Energiebelasting"
                    },
                    {
                        "op": "multiply",
                        "ref": "tax.vat_rate",
                        "factor": "1+x",
                        "label": "21% btw"
                    },
                    {
                        "op": "add",
                        "value": 0.034,
                        "label": "ZonderGas-handling-fee"
                    }
                ]
            },
            "delivered": {
                "strategy": "epex_passthrough",
                "params": []
            }
        },
        "formula": "**Afnemen (per kWh):**\n  EPEX-kwartierprijs\n  + Energiebelasting (tax_rates) — Energiebelasting\n  × (1 + 21% btw (tax_rates)) — 21% btw\n  + €0,0340 — ZonderGas-handling-fee\n\n**Teruglevering (per kWh):**\n  max(0, EPEX-kwartier) × 1,21 (incl. btw)",
        "signup_url": "https://www.zondergas.nl/",
        "notes": "Added 2026-07-13 (eerlijkverbruik.nl). Wederverkoper van EnergyZero (white-label), daarom kwartier-resolutie. Opslag 3,4 ct / vast €6,49 incl btw. TLV niet apart gepubliceerd → EnergyZero-default epex_passthrough (marktprijs incl btw, saldeert) aangenomen — verifieer. Brand-color placeholder — verifieer."
    }
}
